fohm/__init__.py
fohm-0.0.0.dist-info/METADATA
fohm-0.0.0.dist-info/WHEEL
fohm-0.0.0.dist-info/top_level.txt
fohm-0.0.0.dist-info/RECORD
